triones_api/__init__.py
triones_api/api/__init__.py
triones_api/api/api_meta_class.py
triones_api/api/tenant.py
triones_api/config/__init__.py
triones_api/config/api_config.py
triones_api/config/log.py
triones_api/config/response.py
triones_api-0.0.1.dist-info/LICENSE
triones_api-0.0.1.dist-info/METADATA
triones_api-0.0.1.dist-info/WHEEL
triones_api-0.0.1.dist-info/top_level.txt
triones_api-0.0.1.dist-info/RECORD
