Metadata-Version: 2.1
Name: triones-api
Version: 0.0.1
Summary: api methods for Triones.
Home-page: https://git.chengfayun.net/implementation/TrionesAPI
Author: fankailun
Author-email: kailunfan@163.com
License: UNKNOWN
Platform: UNKNOWN
Classifier: Programming Language :: Python :: 3
Classifier: License :: OSI Approved :: MIT License
Classifier: Operating System :: OS Independent
